[
  {
    "model": "core.todo",
    "fields": {
      "request": "Manual QA: Validate admin/admin login succeeds",
      "created_on": "2024-01-01T00:00:00Z",
      "url": "/admin/login/",
      "request_details": "Log in to the Django admin using username 'admin' and password 'admin'. Confirm the login page loads with status 200 and the credential check redirects to the admin dashboard without a 404 or 500 error. After reaching the dashboard, log out and repeat the login to ensure the workflow remains stable.",
      "done_on": null,
      "is_deleted": false,
      "version": "0.1.30"
    }
  }
]
