{
  "coverage": {
    "cp_to_csms": {
      "count": 24,
      "percent": 100.0,
      "supported": [
        "Authorize",
        "BootNotification",
        "ClearedChargingLimit",
        "DataTransfer",
        "FirmwareStatusNotification",
        "Get15118EVCertificate",
        "GetCertificateStatus",
        "Heartbeat",
        "LogStatusNotification",
        "MeterValues",
        "NotifyChargingLimit",
        "NotifyCustomerInformation",
        "NotifyDisplayMessages",
        "NotifyEVChargingNeeds",
        "NotifyEVChargingSchedule",
        "NotifyEvent",
        "NotifyMonitoringReport",
        "NotifyReport",
        "PublishFirmwareStatusNotification",
        "ReportChargingProfiles",
        "SecurityEventNotification",
        "SignCertificate",
        "StatusNotification",
        "TransactionEvent"
      ],
      "total": 24
    },
    "csms_to_cp": {
      "count": 31,
      "percent": 79.49,
      "supported": [
        "CancelReservation",
        "CertificateSigned",
        "ChangeAvailability",
        "ClearCache",
        "ClearChargingProfile",
        "ClearVariableMonitoring",
        "DataTransfer",
        "DeleteCertificate",
        "GetCompositeSchedule",
        "GetInstalledCertificateIds",
        "GetLocalListVersion",
        "GetLog",
        "GetMonitoringReport",
        "GetTransactionStatus",
        "GetVariables",
        "InstallCertificate",
        "PublishFirmware",
        "RequestStartTransaction",
        "RequestStopTransaction",
        "ReserveNow",
        "Reset",
        "SendLocalList",
        "SetChargingProfile",
        "SetMonitoringBase",
        "SetMonitoringLevel",
        "SetVariableMonitoring",
        "SetVariables",
        "TriggerMessage",
        "UnlockConnector",
        "UnpublishFirmware",
        "UpdateFirmware"
      ],
      "total": 39
    },
    "overall": {
      "count": 54,
      "percent": 87.1,
      "supported": [
        "Authorize",
        "BootNotification",
        "CancelReservation",
        "CertificateSigned",
        "ChangeAvailability",
        "ClearCache",
        "ClearChargingProfile",
        "ClearVariableMonitoring",
        "ClearedChargingLimit",
        "DataTransfer",
        "DeleteCertificate",
        "FirmwareStatusNotification",
        "Get15118EVCertificate",
        "GetCertificateStatus",
        "GetCompositeSchedule",
        "GetInstalledCertificateIds",
        "GetLocalListVersion",
        "GetLog",
        "GetMonitoringReport",
        "GetTransactionStatus",
        "GetVariables",
        "Heartbeat",
        "InstallCertificate",
        "LogStatusNotification",
        "MeterValues",
        "NotifyChargingLimit",
        "NotifyCustomerInformation",
        "NotifyDisplayMessages",
        "NotifyEVChargingNeeds",
        "NotifyEVChargingSchedule",
        "NotifyEvent",
        "NotifyMonitoringReport",
        "NotifyReport",
        "PublishFirmware",
        "PublishFirmwareStatusNotification",
        "ReportChargingProfiles",
        "RequestStartTransaction",
        "RequestStopTransaction",
        "ReserveNow",
        "Reset",
        "SecurityEventNotification",
        "SendLocalList",
        "SetChargingProfile",
        "SetMonitoringBase",
        "SetMonitoringLevel",
        "SetVariableMonitoring",
        "SetVariables",
        "SignCertificate",
        "StatusNotification",
        "TransactionEvent",
        "TriggerMessage",
        "UnlockConnector",
        "UnpublishFirmware",
        "UpdateFirmware"
      ],
      "total": 62
    }
  },
  "implemented": {
    "cp_to_csms": [
      "Authorize",
      "BootNotification",
      "ClearedChargingLimit",
      "CostUpdated",
      "DataTransfer",
      "DiagnosticsStatusNotification",
      "FirmwareStatusNotification",
      "Get15118EVCertificate",
      "GetCertificateStatus",
      "Heartbeat",
      "LogStatusNotification",
      "MeterValues",
      "NotifyChargingLimit",
      "NotifyCustomerInformation",
      "NotifyDisplayMessages",
      "NotifyEVChargingNeeds",
      "NotifyEVChargingSchedule",
      "NotifyEvent",
      "NotifyMonitoringReport",
      "NotifyReport",
      "PublishFirmwareStatusNotification",
      "ReportChargingProfiles",
      "ReservationStatusUpdate",
      "SecurityEventNotification",
      "SignCertificate",
      "StartTransaction",
      "StatusNotification",
      "StopTransaction",
      "TransactionEvent"
    ],
    "csms_to_cp": [
      "CancelReservation",
      "CertificateSigned",
      "ChangeAvailability",
      "ChangeConfiguration",
      "ClearCache",
      "ClearChargingProfile",
      "ClearVariableMonitoring",
      "DataTransfer",
      "DeleteCertificate",
      "GetCompositeSchedule",
      "GetConfiguration",
      "GetDiagnostics",
      "GetInstalledCertificateIds",
      "GetLocalListVersion",
      "GetLog",
      "GetMonitoringReport",
      "GetTransactionStatus",
      "GetVariables",
      "InstallCertificate",
      "PublishFirmware",
      "RemoteStartTransaction",
      "RemoteStopTransaction",
      "RequestStartTransaction",
      "RequestStopTransaction",
      "ReserveNow",
      "Reset",
      "SendLocalList",
      "SetChargingProfile",
      "SetMonitoringBase",
      "SetMonitoringLevel",
      "SetVariableMonitoring",
      "SetVariables",
      "TriggerMessage",
      "UnlockConnector",
      "UnpublishFirmware",
      "UpdateFirmware"
    ]
  },
  "spec": {
    "cp_to_csms": [
      "Authorize",
      "BootNotification",
      "ClearedChargingLimit",
      "DataTransfer",
      "FirmwareStatusNotification",
      "Get15118EVCertificate",
      "GetCertificateStatus",
      "Heartbeat",
      "LogStatusNotification",
      "MeterValues",
      "NotifyChargingLimit",
      "NotifyCustomerInformation",
      "NotifyDisplayMessages",
      "NotifyEVChargingNeeds",
      "NotifyEVChargingSchedule",
      "NotifyEvent",
      "NotifyMonitoringReport",
      "NotifyReport",
      "PublishFirmwareStatusNotification",
      "ReportChargingProfiles",
      "SecurityEventNotification",
      "SignCertificate",
      "StatusNotification",
      "TransactionEvent"
    ],
    "csms_to_cp": [
      "CancelReservation",
      "CertificateSigned",
      "ChangeAvailability",
      "ClearCache",
      "ClearChargingProfile",
      "ClearDisplayMessage",
      "ClearVariableMonitoring",
      "CustomerInformation",
      "DataTransfer",
      "DeleteCertificate",
      "GetBaseReport",
      "GetChargingProfiles",
      "GetCompositeSchedule",
      "GetDisplayMessages",
      "GetInstalledCertificateIds",
      "GetLocalListVersion",
      "GetLog",
      "GetMonitoringReport",
      "GetReport",
      "GetTransactionStatus",
      "GetVariables",
      "InstallCertificate",
      "PublishFirmware",
      "RequestStartTransaction",
      "RequestStopTransaction",
      "ReserveNow",
      "Reset",
      "SendLocalList",
      "SetChargingProfile",
      "SetDisplayMessage",
      "SetMonitoringBase",
      "SetMonitoringLevel",
      "SetNetworkProfile",
      "SetVariableMonitoring",
      "SetVariables",
      "TriggerMessage",
      "UnlockConnector",
      "UnpublishFirmware",
      "UpdateFirmware"
    ]
  }
}
