[
  {
    "fields": {
      "github_url": "",
      "is_deleted": false,
      "is_seed_data": true,
      "is_user_data": false,
      "package": [
        "arthexis"
      ],
      "pypi_url": "https://pypi.org/project/arthexis/0.1.18/",
      "release_on": "2025-10-20T04:22:45.014Z",
      "revision": "cd1a993f129582f9da2b7aada93fac98b9e3ec0b",
      "scheduled_date": null,
      "scheduled_time": null,
      "severity": "normal",
      "version": "0.1.18"
    },
    "model": "core.packagerelease"
  }
]
